pitchtrack.py
pitchtrack-0.0.1.dist-info/METADATA
pitchtrack-0.0.1.dist-info/WHEEL
pitchtrack-0.0.1.dist-info/top_level.txt
pitchtrack-0.0.1.dist-info/RECORD
